zestapi/__init__.py
zestapi/cli.py
zestapi/py.typed
zestapi/core/__init__.py
zestapi/core/application.py
zestapi/core/middleware.py
zestapi/core/ratelimit.py
zestapi/core/responses.py
zestapi/core/routing.py
zestapi/core/security.py
zestapi/core/settings.py
zestapi-1.0.1.dist-info/licenses/LICENSE
zestapi-1.0.1.dist-info/METADATA
zestapi-1.0.1.dist-info/WHEEL
zestapi-1.0.1.dist-info/entry_points.txt
zestapi-1.0.1.dist-info/top_level.txt
zestapi-1.0.1.dist-info/RECORD
