Metadata-Version: 2.4
Name: zestapi
Version: 1.0.1
Summary: A modern ASGI-compatible Python framework for building REST APIs with minimal boilerplate
Author-email: Muhammad Adnan Sultan <info.adnansultan@gmail.com>
License: MIT
Project-URL: Homepage, https://github.com/madnansultandotme/zestapi-python
Project-URL: Documentation, https://github.com/madnansultandotme/zestapi-python/blob/main/docs/
Project-URL: Repository, https://github.com/madnansultandotme/zestapi-python
Project-URL: Issues, https://github.com/madnansultandotme/zestapi-python/issues
Project-URL: Changelog, https://github.com/madnansultandotme/zestapi-python/blob/main/CHANGELOG.md
Project-URL: Security, https://github.com/madnansultandotme/zestapi-python/blob/main/SECURITY.md
Keywords: api,web,framework,asgi,rest,microservice
Classifier: Development Status :: 5 - Production/Stable
Classifier: Intended Audience :: Developers
Classifier: License :: OSI Approved :: MIT License
Classifier: Operating System :: OS Independent
Classifier: Programming Language :: Python :: 3
Classifier: Programming Language :: Python :: 3.10
Classifier: Programming Language :: Python :: 3.11
Classifier: Programming Language :: Python :: 3.12
Classifier: Topic :: Internet :: WWW/HTTP :: HTTP Servers
Classifier: Topic :: Internet :: WWW/HTTP :: WSGI :: Application
Classifier: Topic :: Software Development :: Libraries :: Application Frameworks
Classifier: Topic :: Software Development :: Libraries :: Python Modules
Requires-Python: >=3.10
License-File: LICENSE
Requires-Dist: starlette>=0.46.0
Requires-Dist: uvicorn[standard]>=0.30.0
Requires-Dist: orjson>=3.10.0
Requires-Dist: python-jose[cryptography]>=3.3.0
Requires-Dist: pydantic>=2.5.0
Requires-Dist: pydantic-settings>=2.0.0
Requires-Dist: python-multipart>=0.0.6
Requires-Dist: python-dotenv>=1.0.0
Provides-Extra: dev
Requires-Dist: pytest>=7.0.0; extra == "dev"
Requires-Dist: pytest-asyncio>=0.21.0; extra == "dev"
Requires-Dist: coverage>=7.0.0; extra == "dev"
Requires-Dist: httpx>=0.25.0; extra == "dev"
Requires-Dist: black>=23.0.0; extra == "dev"
Requires-Dist: isort>=5.12.0; extra == "dev"
Requires-Dist: flake8>=6.0.0; extra == "dev"
Requires-Dist: mypy>=1.5.0; extra == "dev"
Requires-Dist: build>=0.10.0; extra == "dev"
Requires-Dist: twine>=4.0.0; extra == "dev"
Requires-Dist: pre-commit>=3.0.0; extra == "dev"
Provides-Extra: test
Requires-Dist: pytest>=7.0.0; extra == "test"
Requires-Dist: pytest-asyncio>=0.21.0; extra == "test"
Requires-Dist: coverage>=7.0.0; extra == "test"
Requires-Dist: httpx>=0.25.0; extra == "test"
Provides-Extra: docs
Requires-Dist: mkdocs>=1.5.0; extra == "docs"
Requires-Dist: mkdocs-material>=9.0.0; extra == "docs"
Requires-Dist: mkdocstrings[python]>=0.20.0; extra == "docs"
Dynamic: license-file
